{
  "iri": "http://www.ebi.ac.uk/efo/EFO_0002571",
  "lang": "en",
  "description": [
    "An activity that produces an effect, or that is intended to alter the course of a disease in a patient or population. This is a general term that encompasses the medical, social, behavioral, and environmental acts that can have preventive, therapeutic, or palliative effects."
  ],
  "synonyms": [
    "SURGICAL AND MEDICAL PROCEDURES",
    "Interventional",
    "interventionDescription",
    "Intervention Strategies",
    "Intervention or Procedure",
    "Intervention",
    "Procedure"
  ],
  "annotation": {
    "database_cross_reference": [
      "NCIt:C25218",
      "SNOMEDCT:50731006",
      "ICD10:Z41",
      "NCIt:C79751"
    ],
    "gwas_trait": [
      "true"
    ],
    "term editor": [
      "Tomasz Adamusiak",
      "Jie Zheng"
    ]
  },
  "label": "medical procedure",
  "ontology_name": "efo",
  "ontology_prefix": "EFO",
  "ontology_iri": "http://www.ebi.ac.uk/efo/efo.owl",
  "is_obsolete": false,
  "term_replaced_by": null,
  "is_defining_ontology": true,
  "has_children": true,
  "is_root": false,
  "short_form": "EFO_0002571",
  "obo_id": "EFO:0002571",
  "in_subset": null,
  "obo_definition_citation": null,
  "obo_xref": [
    {
      "database": "ICD10",
      "id": "Z41",
      "description": null,
      "url": null
    },
    {
      "database": "NCIt",
      "id": "C79751",
      "description": null,
      "url": null
    },
    {
      "database": "SNOMEDCT",
      "id": "50731006",
      "description": null,
      "url": null
    },
    {
      "database": "NCIt",
      "id": "C25218",
      "description": null,
      "url": null
    }
  ],
  "obo_synonym": null,
  "is_preferred_root": false,
  "_links": {
    "self": {
      "href": "https://www.ebi.ac.uk/ols/api/ontologies/efo/terms/http%253A%252F%252Fwww.ebi.ac.uk%252Fefo%252FEFO_0002571?lang=en"
    },
    "parents": {
      "href": "https://www.ebi.ac.uk/ols/api/ontologies/efo/terms/http%253A%252F%252Fwww.ebi.ac.uk%252Fefo%252FEFO_0002571/parents"
    },
    "ancestors": {
      "href": "https://www.ebi.ac.uk/ols/api/ontologies/efo/terms/http%253A%252F%252Fwww.ebi.ac.uk%252Fefo%252FEFO_0002571/ancestors"
    },
    "hierarchicalParents": {
      "href": "https://www.ebi.ac.uk/ols/api/ontologies/efo/terms/http%253A%252F%252Fwww.ebi.ac.uk%252Fefo%252FEFO_0002571/hierarchicalParents"
    },
    "hierarchicalAncestors": {
      "href": "https://www.ebi.ac.uk/ols/api/ontologies/efo/terms/http%253A%252F%252Fwww.ebi.ac.uk%252Fefo%252FEFO_0002571/hierarchicalAncestors"
    },
    "jstree": {
      "href": "https://www.ebi.ac.uk/ols/api/ontologies/efo/terms/http%253A%252F%252Fwww.ebi.ac.uk%252Fefo%252FEFO_0002571/jstree"
    },
    "children": {
      "href": "https://www.ebi.ac.uk/ols/api/ontologies/efo/terms/http%253A%252F%252Fwww.ebi.ac.uk%252Fefo%252FEFO_0002571/children"
    },
    "descendants": {
      "href": "https://www.ebi.ac.uk/ols/api/ontologies/efo/terms/http%253A%252F%252Fwww.ebi.ac.uk%252Fefo%252FEFO_0002571/descendants"
    },
    "hierarchicalChildren": {
      "href": "https://www.ebi.ac.uk/ols/api/ontologies/efo/terms/http%253A%252F%252Fwww.ebi.ac.uk%252Fefo%252FEFO_0002571/hierarchicalChildren"
    },
    "hierarchicalDescendants": {
      "href": "https://www.ebi.ac.uk/ols/api/ontologies/efo/terms/http%253A%252F%252Fwww.ebi.ac.uk%252Fefo%252FEFO_0002571/hierarchicalDescendants"
    },
    "graph": {
      "href": "https://www.ebi.ac.uk/ols/api/ontologies/efo/terms/http%253A%252F%252Fwww.ebi.ac.uk%252Fefo%252FEFO_0002571/graph"
    }
  },
  "errors": [],
  "warnings": []
}
